provenance_drop_from_schema_operator/__init__.py
provenance_drop_from_schema_operator/provenance_drop_from_schema_operator.py
amsterdam_airflow_provenance_drop_from_schema_operator-1.3.dist-info/METADATA
amsterdam_airflow_provenance_drop_from_schema_operator-1.3.dist-info/LICENSE.txt
amsterdam_airflow_provenance_drop_from_schema_operator-1.3.dist-info/WHEEL
amsterdam_airflow_provenance_drop_from_schema_operator-1.3.dist-info/RECORD
