Metadata-Version: 2.1
Name: amsterdam-airflow-provenance-drop-from-schema-operator
Version: 1.3
Summary: Amsterdam Airflow operator: provenance_drop_from_schema_operator
Home-page: https://amsterdam.nl
License: MIT
Keywords: airflow,operators
Author: Amsterdam
Author-email: welcome@amsterdam.nl
Maintainer: Amsterdam
Maintainer-email: welcome@amsterdam.nl
Requires-Python: >=3.9,<4.0
Classifier: License :: OSI Approved :: MIT License
Classifier: Programming Language :: Python :: 3
Classifier: Programming Language :: Python :: 3.9
Classifier: Programming Language :: Python :: 3.10
Classifier: Programming Language :: Python :: 3.11
Classifier: Topic :: Software Development :: Libraries :: Python Modules
Requires-Dist: amsterdam-airflow-postgres-on-azure-hook (==1.0)
Requires-Dist: amsterdam-airflow-xcom-attr-assigner-mixin (==1.0)
Requires-Dist: amsterdam-schema-tools (==5.1.3)
Requires-Dist: apache-airflow (==2.4.1)
Requires-Dist: apache-airflow-providers-postgres (==2.4.0)
Requires-Dist: cachecontrol[filecache] (>=0.12.9,<0.13.0)
Requires-Dist: poetry-core (>=1.1.0b3,<2.0.0)
Requires-Dist: poetry-plugin-export (>=1.0.5,<2.0.0)
